{
  "discussions": [
    {
      "idMovie": "1125899",
      "topics": [
        {
          "topicId": "72a1bb44-a433-46be-9b6a-8fc025fac33a",
          "title": "asdasdasd",
          "message": "asdasdasd",
          "timestamp": "2025-04-04T12:00:00Z",
          "responses": []
        },
        {
          "topicId": "d981a0c1-b557-4d50-bf6e-321672ad9ee9",
          "title": "xd",
          "message": "xd",
          "timestamp": "2025-04-04T12:00:00Z",
          "responses": []
        }
      ]
    },
    {
      "idMovie": "950387",
      "topics": [
        {
          "topicId": "431d6d8c-90cf-4269-abd0-995c6bc54ace",
          "title": "momoabord",
          "message": "que epetaculo",
          "timestamp": "2025-04-04T12:00:00Z",
          "responses": []
        }
      ]
    },
    {
      "idMovie": "1197306",
      "topics": [
        {
          "topicId": "1f0eea4b-2a76-41bf-9df7-8071c6e4fbcd",
          "title": "mira como te mira el dolape",
          "message": "doma el dolape que dicen?",
          "timestamp": "2025-04-04T12:00:00Z",
          "responses": []
        },
        {
          "topicId": "b586f6f8-727a-4c0e-a57f-144cd5c9bc6e",
          "title": "asdasd",
          "message": "asdasdasd",
          "timestamp": "2025-04-04T12:00:00Z",
          "responses": []
        }
      ]
    },
    {
      "idMovie": "1261050",
      "topics": [
        {
          "topicId": "b95c589a-5a4c-40be-b45d-b326ceb56c59",
          "title": "la peppouuunaaaa",
          "message": "que epetaculooo",
          "timestamp": "2025-04-07T23:44:42.822Z",
          "responses": []
        }
      ]
    }
  ]
}